[
    {
        "id": 1,
        "name": "Bharni Style",
        "price": 1599,
        "rating": 4.5,
        "image": "images/bharni.jpg"
    },
    {
        "id": 2,
        "name": "Katchni Style",
        "price": 1599,
        "rating": 4.7,
        "image": "images/katchni.jpg"
    },
    {
        "id": 3,
        "name": "Gonda Style",
        "price": 7299,
        "rating": 4.2,
        "image": "images/gonda.jpg"
    },
    {
        "id": 4,
        "name": "Tantrik  Style",
        "price": 1799,
        "rating": 4.8,
        "image": "images/tantrik.jpg"
    },
    {
        "id": 5,
        "name": "Handmade Pottery",
        "price": 799,
        "rating": 4.0,
        "image": "images/handmade.jpg"
    },
    {
        "id": 6,
        "name": "Brass Cutting",
        "price": 1599,
        "rating": 4.3,
        "image": "images/brass.jpg"
    },
    {
        "id": 7,
        "name": "Silver Oxidised Braclete",
        "price": 3599,
        "rating": 4.6,
        "image": "images/snake.jpg"
    },
    {
        "id": 8,
        "name": "Arjun Rath",
        "price": 9599,
        "rating": 4.9,
        "image": "images/rath.jpg"
    },
    {
        "id": 9,
        "name": "Ban Bati Metal",
        "price": 4199,
        "rating": 4.4,
        "image": "images/bati.jpg"
    },
    {
        "id": 10,
        "name": "Ethinic Bell Metal Tray",
        "price": 759,
        "rating": 4.1,
        "image": "images/metaltray.jpg"
    },
    {
        "id": 11,
        "name": "Kadhai",
        "price": 1299,
        "rating": 4.5,
        "image": "images/kadai.jpg"
    }
]
